<annotation>
	<folder>JPEGImages</folder>
	<filename>adi16.jpg</filename>
	<path>C:\Users\Kohli\Documents\Projects\Github\Object-Detection\Logo2-Dataset\JPEGImages\adi16.jpg</path>
	<source>
		<database>Unknown</database>
	</source>
	<size>
		<width>1000</width>
		<height>1000</height>
		<depth>3</depth>
	</size>
	<segmented>0</segmented>
	<object>
		<name>adi</name>
		<pose>Unspecified</pose>
		<truncated>0</truncated>
		<difficult>0</difficult>
		<bndbox>
			<xmin>435</xmin>
			<ymin>335</ymin>
			<xmax>541</xmax>
			<ymax>397</ymax>
		</bndbox>
	</object>
	<object>
		<name>adi</name>
		<pose>Unspecified</pose>
		<truncated>0</truncated>
		<difficult>0</difficult>
		<bndbox>
			<xmin>450</xmin>
			<ymin>798</ymin>
			<xmax>548</xmax>
			<ymax>865</ymax>
		</bndbox>
	</object>
</annotation>
